Workbook

Sheet Dashboard
A1: Olist E-Commerce Sales & Delivery Analysis
A2: Excel project | Sample of 2,000 Olist-style orders (Jan 2017 - Aug 2018) | All numbers are live formulas
A4: Total Orders | B4: Revenue | C4: Net Profit | D4: Profit Margin | E4: Avg Delivery Days | F4: On-Time % | G4: Avg Review Score
A5: =COUNTA(Data!$A$2:$A$2001) -> 2000 | B5: =SUM(Data!$P$2:$P$2001) -> 264925.66 | C5: =SUM(Data!$S$2:$S$2001) -> 50856.568 | D5: =C5/B5 -> 0.19196543 | E5: =AVERAGE(Data!$M$2:$M$2001) -> 12.45 | F5: =SUM(Data!$O$2:$O$2001)/COUNTA(Data!$A$2:$A$2001) -> 0.9275 | G5: =AVERAGE(Data!$J$2:$J$2001) -> 4.2145
A7: Top State by Orders | B7: Top State by Margin | C7: Slowest Delivery State | D7: Peak Sales Month | E7: Top Category by Profit | F7: States: High Volume, Low Margin | G7: Late Orders %
A8: =INDEX('State Analysis'!$A$5:$A$16,MATCH(MAX('State Analysis'!$B$5:$B$16),'State Analysis'!$B$5:$B$16,0)) -> SP | B8: =INDEX('State Analysis'!$A$5:$A$16,MATCH(MAX('State Analysis'!$F$5:$F$16),'State Analysis'!$F$5:$F$16,0)) -> SP | C8: =INDEX('State Analysis'!$A$5:$A$16,MATCH(MAX('State Analysis'!$J$5:$J$16),'State Analysis'!$J$5:$J$16,0)) -> PE | D8: =INDEX('Monthly Trend'!$A$5:$A$24,MATCH(MAX('Monthly Trend'!$B$5:$B$24),'Monthly Trend'!$B$5:$B$24,0)) -> 43313 | E8: =INDEX('Category Analysis'!$A$5:$A$13,MATCH(1,'Category Analysis'!$I$5:$I$13,0)) -> health_beauty | F8: =COUNTIF('State Analysis'!$O$5:$O$16,"High volume, low margin") -> 1 | G8: =1-F5 -> 0.0725
A10: Key Insights (auto-generated from formulas)
A11: ="1. "&INDEX('State Analysis'!$A$5:$A$16,MATCH(SUMPRODUCT(MAX(('State Analysis'!$L$5:$L$16<=4)*'State Analysis'!$M$5:$M$16)),'State Analysis'!$M$5:$M$16,0))&" is a top-4 state by orders ("&TEXT(INDEX('State Analysis'!$C$5:$C$16,MATCH(SUMPRODUCT(MAX(('State Analysis'!$L$5:$L$16<=4)*'State Analysis'!$M$5:$M$16)),'State Analysis'!$M$5:$M$16,0)),"0.0%")&" of volume) yet ranks #"&SUMPRODUCT(MAX(('State Analysis'!$L$5:$L$16<=4)*'State Analysis'!$M$5:$M$16))&" of 12 on margin ("&TEXT(INDEX('State Analysis'!$F$5:$F$16,MATCH(SUMPRODUCT(MAX(('State Analysis'!$L$5:$L$16<=4)*'State Analysis'!$M$5:$M$16)),'State Analysis'!$M$5:$M$16,0)),"0.0%")&" vs "&TEXT(MAX('State Analysis'!$F$5:$F$16),"0.0%")&" for "&B8&") - high order volume does not mean higher profit." -> 1. RJ is a top-4 state by orders (12.6% of volume) yet ranks #8 of 12 on margin (17.0% vs 21.8% for SP) - high order volume does not mean higher profit.
A12: ="2. "&INDEX('State Analysis'!$A$5:$A$16,MATCH(MIN('State Analysis'!$F$5:$F$16),'State Analysis'!$F$5:$F$16,0))&" has the weakest margin ("&TEXT(MIN('State Analysis'!$F$5:$F$16),"0.0%")&"): avg freight "&TEXT(INDEX('State Analysis'!$I$5:$I$16,MATCH(MIN('State Analysis'!$F$5:$F$16),'State Analysis'!$F$5:$F$16,0)),"0.00")&" vs "&TEXT('State Analysis'!$I$17,"0.00")&" overall, so shipping cost eats into profit." -> 2. BA has the weakest margin (11.3%): avg freight 32.07 vs 21.95 overall, so shipping cost eats into profit.
A13: ="3. "&C8&" is the likely delivery bottleneck: "&TEXT(MAX('State Analysis'!$J$5:$J$16),"0.0")&" avg days vs "&TEXT(E5,"0.0")&" overall, with "&TEXT(INDEX('State Analysis'!$K$5:$K$16,MATCH(C8,'State Analysis'!$A$5:$A$16,0)),"0.0%")&" on-time." -> 3. PE is the likely delivery bottleneck: 23.5 avg days vs 12.5 overall, with 90.5% on-time.
A14: ="4. Orders delivered in 22+ days score "&TEXT('Delivery Analysis'!D8,"0.00")&" on reviews vs "&TEXT('Delivery Analysis'!D5,"0.00")&" for 0-7 days; late orders lose "&TEXT('Delivery Analysis'!D14,"0.00")&" review points." -> 4. Orders delivered in 22+ days score 3.14 on reviews vs 4.42 for 0-7 days; late orders lose 1.67 review points.
A15: ="5. Peak demand was "&TEXT(D8,"mmm-yyyy")&"; "&F8&" top-4 volume state(s) rank in the bottom half for margin (see State Analysis, Insight Flag)." -> 5. Peak demand was Aug-2018; 1 top-4 volume state(s) rank in the bottom half for margin (see State Analysis, Insight Flag).
A17: State Drill-down (pick a state in the yellow cell)
A18: Select State | B18: SP
A19: Orders | B19: =INDEX('State Analysis'!$B$5:$B$16,MATCH($B$18,'State Analysis'!$A$5:$A$16,0)) -> 909
A20: Revenue | B20: =INDEX('State Analysis'!$D$5:$D$16,MATCH($B$18,'State Analysis'!$A$5:$A$16,0)) -> 115617.11
A21: Net Profit | B21: =INDEX('State Analysis'!$E$5:$E$16,MATCH($B$18,'State Analysis'!$A$5:$A$16,0)) -> 25250.605
A22: Profit Margin | B22: =INDEX('State Analysis'!$F$5:$F$16,MATCH($B$18,'State Analysis'!$A$5:$A$16,0)) -> 0.21839851
A23: Avg Delivery Days | B23: =INDEX('State Analysis'!$J$5:$J$16,MATCH($B$18,'State Analysis'!$A$5:$A$16,0)) -> 8.6567657
A24: On-Time % | B24: =INDEX('State Analysis'!$K$5:$K$16,MATCH($B$18,'State Analysis'!$A$5:$A$16,0)) -> 0.94609461
A25: Volume Rank (of 12) | B25: =INDEX('State Analysis'!$L$5:$L$16,MATCH($B$18,'State Analysis'!$A$5:$A$16,0)) -> 1
A26: Margin Rank (of 12) | B26: =INDEX('State Analysis'!$M$5:$M$16,MATCH($B$18,'State Analysis'!$A$5:$A$16,0)) -> 1

Sheet Data
A1: order_id | B1: customer_state | C1: purchase_date | D1: delivered_date | E1: estimated_date | F1: product_category | G1: price | H1: freight_value | I1: payment_type | J1: review_score | K1: order_status | L1: order_month | M1: delivery_days | N1: delay_days | O1: on_time | P1: revenue | Q1: cogs | R1: freight_absorbed | S1: net_profit | T1: delivery_bucket
A2: ad3e8705cd525f9feb67a72c8ee0314d | B2: SP | C2: 42738 | D2: 42748 | E2: 42752 | F2: toys | G2: 83.12 | H2: 19.21 | I2: credit_card | J2: 5 | K2: delivered | L2: =DATE(YEAR(C2),MONTH(C2),1) -> 42736 | M2: =D2-C2 -> 10 | N2: =MAX(0,D2-E2) -> 0 | O2: =IF(D2<=E2,1,0) -> 1 | P2: =G2+H2 -> 102.33 | Q2: =G2*INDEX(Assumptions!$B$8:$B$16,MATCH(F2,Assumptions!$A$8:$A$16,0)) -> 49.872 | R2: =H2*Assumptions!$B$3 -> 11.526 | S2: =G2-Q2-R2 -> 21.722 | T2: =IF(M2<=7,"0-7 days",IF(M2<=14,"8-14 days",IF(M2<=21,"15-21 days","22+ days"))) -> 8-14 days
A3: 63b55bfb128e92ad6b707ef6fe62314e | B3: PR | C3: 42738 | D3: 42750 | E3: 42761 | F3: health_beauty | G3: 60.51 | H3: 16.47 | I3: voucher | J3: 4 | K3: delivered | L3: =DATE(YEAR(C3),MONTH(C3),1) -> 42736 | M3: =D3-C3 -> 12 | N3: =MAX(0,D3-E3) -> 0 | O3: =IF(D3<=E3,1,0) -> 1 | P3: =G3+H3 -> 76.98 | Q3: =G3*INDEX(Assumptions!$B$8:$B$16,MATCH(F3,Assumptions!$A$8:$A$16,0)) -> 35.0958 | R3: =H3*Assumptions!$B$3 -> 9.882 | S3: =G3-Q3-R3 -> 15.5322 | T3: =IF(M3<=7,"0-7 days",IF(M3<=14,"8-14 days",IF(M3<=21,"15-21 days","22+ days"))) -> 8-14 days
A4: c18cc4131d848484424526028f016e18 | B4: RS | C4: 42738 | D4: 42760 | E4: 42764 | F4: computers_accessories | G4: 134.74 | H4: 25 | I4: credit_card | J4: 3 | K4: delivered | L4: =DATE(YEAR(C4),MONTH(C4),1) -> 42736 | M4: =D4-C4 -> 22 | N4: =MAX(0,D4-E4) -> 0 | O4: =IF(D4<=E4,1,0) -> 1 | P4: =G4+H4 -> 159.74 | Q4: =G4*INDEX(Assumptions!$B$8:$B$16,MATCH(F4,Assumptions!$A$8:$A$16,0)) -> 99.7076 | R4: =H4*Assumptions!$B$3 -> 15 | S4: =G4-Q4-R4 -> 20.0324 | T4: =IF(M4<=7,"0-7 days",IF(M4<=14,"8-14 days",IF(M4<=21,"15-21 days","22+ days"))) -> 22+ days
A5: e88188c3788f06ed3c1e919bee5a4007 | B5: RJ | C5: 42740 | D5: 42754 | E5: 42763 | F5: computers_accessories | G5: 40.74 | H5: 16.28 | I5: credit_card | J5: 5 | K5: delivered | L5: =DATE(YEAR(C5),MONTH(C5),1) -> 42736 | M5: =D5-C5 -> 14 | N5: =MAX(0,D5-E5) -> 0 | O5: =IF(D5<=E5,1,0) -> 1 | P5: =G5+H5 -> 57.02 | Q5: =G5*INDEX(Assumptions!$B$8:$B$16,MATCH(F5,Assumptions!$A$8:$A$16,0)) -> 30.1476 | R5: =H5*Assumptions!$B$3 -> 9.768 | S5: =G5-Q5-R5 -> 0.8244 | T5: =IF(M5<=7,"0-7 days",IF(M5<=14,"8-14 days",IF(M5<=21,"15-21 days","22+ days"))) -> 8-14 days
A6: b789593e216dfc7021965beeda3544b5 | B6: SP | C6: 42740 | D6: 42754 | E6: 42757 | F6: auto | G6: 47.62 | H6: 13.02 | I6: credit_card | J6: 5 | K6: delivered | L6: =DATE(YEAR(C6),MONTH(C6),1) -> 42736 | M6: =D6-C6 -> 14 | N6: =MAX(0,D6-E6) -> 0 | O6: =IF(D6<=E6,1,0) -> 1 | P6: =G6+H6 -> 60.64 | Q6: =G6*INDEX(Assumptions!$B$8:$B$16,MATCH(F6,Assumptions!$A$8:$A$16,0)) -> 32.3816 | R6: =H6*Assumptions!$B$3 -> 7.812 | S6: =G6-Q6-R6 -> 7.4264 | T6: =IF(M6<=7,"0-7 days",IF(M6<=14,"8-14 days",IF(M6<=21,"15-21 days","22+ days"))) -> 8-14 days
A7: 912cf322735e81531c3892e8f2cfcd63 | B7: RS | C7: 42741 | D7: 42757 | E7: 42765 | F7: sports_leisure | G7: 125.89 | H7: 20.72 | I7: boleto | J7: 4 | K7: delivered | L7: =DATE(YEAR(C7),MONTH(C7),1) -> 42736 | M7: =D7-C7 -> 16 | N7: =MAX(0,D7-E7) -> 0 | O7: =IF(D7<=E7,1,0) -> 1 | P7: =G7+H7 -> 146.61 | Q7: =G7*INDEX(Assumptions!$B$8:$B$16,MATCH(F7,Assumptions!$A$8:$A$16,0)) -> 80.5696 | R7: =H7*Assumptions!$B$3 -> 12.432 | S7: =G7-Q7-R7 -> 32.8884 | T7: =IF(M7<=7,"0-7 days",IF(M7<=14,"8-14 days",IF(M7<=21,"15-21 days","22+ days"))) -> 15-21 days
A8: 14a9ee59eb1313b795d14b6d6e9ae156 | B8: MG | C8: 42744 | D8: 42761 | E8: 42767 | F8: auto | G8: 119.5 | H8: 26.65 | I8: credit_card | J8: 4 | K8: delivered | L8: =DATE(YEAR(C8),MONTH(C8),1) -> 42736 | M8: =D8-C8 -> 17 | N8: =MAX(0,D8-E8) -> 0 | O8: =IF(D8<=E8,1,0) -> 1 | P8: =G8+H8 -> 146.15 | Q8: =G8*INDEX(Assumptions!$B$8:$B$16,MATCH(F8,Assumptions!$A$8:$A$16,0)) -> 81.26 | R8: =H8*Assumptions!$B$3 -> 15.99 | S8: =G8-Q8-R8 -> 22.25 | T8: =IF(M8<=7,"0-7 days",IF(M8<=14,"8-14 days",IF(M8<=21,"15-21 days","22+ days"))) -> 15-21 days
A9: 094f51660bae6d2bfbece5d5a8856294 | B9: SP | C9: 42744 | D9: 42761 | E9: 42763 | F9: watches_gifts | G9: 280.85 | H9: 22.93 | I9: credit_card | J9: 5 | K9: delivered | L9: =DATE(YEAR(C9),MONTH(C9),1) -> 42736 | M9: =D9-C9 -> 17 | N9: =MAX(0,D9-E9) -> 0 | O9: =IF(D9<=E9,1,0) -> 1 | P9: =G9+H9 -> 303.78 | Q9: =G9*INDEX(Assumptions!$B$8:$B$16,MATCH(F9,Assumptions!$A$8:$A$16,0)) -> 185.361 | R9: =H9*Assumptions!$B$3 -> 13.758 | S9: =G9-Q9-R9 -> 81.731 | T9: =IF(M9<=7,"0-7 days",IF(M9<=14,"8-14 days",IF(M9<=21,"15-21 days","22+ days"))) -> 15-21 days
A10: 0534a1018ddce71981f38dd4fd034ada | B10: SP | C10: 42747 | D10: 42753 | E10: 42762 | F10: auto | G10: 42.07 | H10: 16.67 | I10: credit_card | J10: 4 | K10: delivered | L10: =DATE(YEAR(C10),MONTH(C10),1) -> 42736 | M10: =D10-C10 -> 6 | N10: =MAX(0,D10-E10) -> 0 | O10: =IF(D10<=E10,1,0) -> 1 | P10: =G10+H10 -> 58.74 | Q10: =G10*INDEX(Assumptions!$B$8:$B$16,MATCH(F10,Assumptions!$A$8:$A$16,0)) -> 28.6076 | R10: =H10*Assumptions!$B$3 -> 10.002 | S10: =G10-Q10-R10 -> 3.4604 | T10: =IF(M10<=7,"0-7 days",IF(M10<=14,"8-14 days",IF(M10<=21,"15-21 days","22+ days"))) -> 0-7 days
A11: 8ff63d7ed92fcf511e8124950bd515dd | B11: MG | C11: 42747 | D11: 42758 | E11: 42769 | F11: bed_bath_table | G11: 83.04 | H11: 23.66 | I11: credit_card | J11: 4 | K11: delivered | L11: =DATE(YEAR(C11),MONTH(C11),1) -> 42736 | M11: =D11-C11 -> 11 | N11: =MAX(0,D11-E11) -> 0 | O11: =IF(D11<=E11,1,0) -> 1 | P11: =G11+H11 -> 106.7 | Q11: =G11*INDEX(Assumptions!$B$8:$B$16,MATCH(F11,Assumptions!$A$8:$A$16,0)) -> 51.4848 | R11: =H11*Assumptions!$B$3 -> 14.196 | S11: =G11-Q11-R11 -> 17.3592 | T11: =IF(M11<=7,"0-7 days",IF(M11<=14,"8-14 days",IF(M11<=21,"15-21 days","22+ days"))) -> 8-14 days
A12: e3f2df80a7bbc6129a37ef9d5983ce94 | B12: SP | C12: 42749 | D12: 42761 | E12: 42765 | F12: watches_gifts | G12: 96.56 | H12: 12.89 | I12: credit_card | J12: 4 | K12: delivered | L12: =DATE(YEAR(C12),MONTH(C12),1) -> 42736 | M12: =D12-C12 -> 12 | N12: =MAX(0,D12-E12) -> 0 | O12: =IF(D12<=E12,1,0) -> 1 | P12: =G12+H12 -> 109.45 | Q12: =G12*INDEX(Assumptions!$B$8:$B$16,MATCH(F12,Assumptions!$A$8:$A$16,0)) -> 63.7296 | R12: =H12*Assumptions!$B$3 -> 7.734 | S12: =G12-Q12-R12 -> 25.0964 | T12: =IF(M12<=7,"0-7 days",IF(M12<=14,"8-14 days",IF(M12<=21,"15-21 days","22+ days"))) -> 8-14 days
A13: c1f857c42726c2c37af468fdfa6965f1 | B13: SP | C13: 42751 | D13: 42760 | E13: 42768 | F13: sports_leisure | G13: 40.63 | H13: 17.32 | I13: boleto | J13: 4 | K13: delivered | L13: =DATE(YEAR(C13),MONTH(C13),1) -> 42736 | M13: =D13-C13 -> 9 | N13: =MAX(0,D13-E13) -> 0 | O13: =IF(D13<=E13,1,0) -> 1 | P13: =G13+H13 -> 57.95 | Q13: =G13*INDEX(Assumptions!$B$8:$B$16,MATCH(F13,Assumptions!$A$8:$A$16,0)) -> 26.0032 | R13: =H13*Assumptions!$B$3 -> 10.392 | S13: =G13-Q13-R13 -> 4.2348 | T13: =IF(M13<=7,"0-7 days",IF(M13<=14,"8-14 days",IF(M13<=21,"15-21 days","22+ days"))) -> 8-14 days
... A2001: 66bd7b2feedab4fe4cfa768713791994 | B2001: BA | C2001: 43343 | D2001: 43368 | E2001: 43377 | F2001: furniture_decor | G2001: 102.59 | H2001: 30.81 | I2001: credit_card | J2001: 3 | K2001: delivered | L2001: =DATE(YEAR(C2001),MONTH(C2001),1) -> 43313 | M2001: =D2001-C2001 -> 25 | N2001: =MAX(0,D2001-E2001) -> 0 | O2001: =IF(D2001<=E2001,1,0) -> 1 | P2001: =G2001+H2001 -> 133.4 | Q2001: =G2001*INDEX(Assumptions!$B$8:$B$16,MATCH(F2001,Assumptions!$A$8:$A$16,0)) -> 71.813 | R2001: =H2001*Assumptions!$B$3 -> 18.486 | S2001: =G2001-Q2001-R2001 -> 12.291 | T2001: =IF(M2001<=7,"0-7 days",IF(M2001<=14,"8-14 days",IF(M2001<=21,"15-21 days","22+ days"))) -> 22+ days

Sheet Assumptions
A1: Assumptions & Notes
A3: Share of freight absorbed by the platform | B3: 0.6 | C3: Assumption (editable): Olist data has no cost data, so this is my modelling input.
A5: Cost of goods as % of price, by category (assumed)
A7: Category | B7: Cost Ratio
A8: bed_bath_table | B8: 0.62
A9: health_beauty | B9: 0.58
A10: sports_leisure | B10: 0.64
A11: furniture_decor | B11: 0.7
A12: computers_accessories | B12: 0.74
A13: watches_gifts | B13: 0.66
A14: housewares | B14: 0.63
A15: toys | B15: 0.6
A16: auto | B16: 0.68
A19: Legend: blue text / yellow fill = editable input. Change it and every sheet recalculates.
A21: Data note: this workbook uses a 2,000-order SAMPLE with the same column structure as the Olist Brazilian
A22: E-Commerce dataset (Kaggle). Replace the Data sheet (columns A-K) with real Olist rows and all formulas update.
A23: Profit = Price - COGS (price x category cost ratio) - absorbed freight (freight x absorb %).
A24: Only delivered orders are included.

Sheet State Analysis
A1: Sales & Delivery Analysis by State
A2: All figures are formulas on the Data sheet (COUNTIFS / SUMIFS / AVERAGEIFS / RANK).
A4: State | B4: Orders | C4: Order Share | D4: Revenue | E4: Net Profit | F4: Profit Margin | G4: Profit / Order | H4: Avg Order Value | I4: Avg Freight | J4: Avg Delivery Days | K4: On-Time % | L4: Volume Rank | M4: Margin Rank | N4: Rank Gap | O4: Insight Flag
A5: SP | B5: =COUNTIFS(Data!$B$2:$B$2001,A5) -> 909 | C5: =B5/$B$17 -> 0.4545 | D5: =SUMIFS(Data!$P$2:$P$2001,Data!$B$2:$B$2001,A5) -> 115617.11 | E5: =SUMIFS(Data!$S$2:$S$2001,Data!$B$2:$B$2001,A5) -> 25250.605 | F5: =IFERROR(E5/D5,0) -> 0.21839851 | G5: =IFERROR(E5/B5,0) -> 27.778443 | H5: =IFERROR(D5/B5,0) -> 127.19154 | I5: =IFERROR(AVERAGEIFS(Data!$H$2:$H$2001,Data!$B$2:$B$2001,A5),0) -> 17.822387 | J5: =IFERROR(AVERAGEIFS(Data!$M$2:$M$2001,Data!$B$2:$B$2001,A5),0) -> 8.6567657 | K5: =IFERROR(SUMIFS(Data!$O$2:$O$2001,Data!$B$2:$B$2001,A5)/B5,0) -> 0.94609461 | L5: =RANK(B5,$B$5:$B$16) -> 1 | M5: =RANK(F5,$F$5:$F$16) -> 1 | N5: =M5-L5 -> 0 | O5: =IF(AND(L5<=4,M5>=7),"High volume, low margin",IF(AND(L5>=7,M5<=4),"Low volume, high margin",""))
A6: RJ | B6: =COUNTIFS(Data!$B$2:$B$2001,A6) -> 252 | C6: =B6/$B$17 -> 0.126 | D6: =SUMIFS(Data!$P$2:$P$2001,Data!$B$2:$B$2001,A6) -> 32089.61 | E6: =SUMIFS(Data!$S$2:$S$2001,Data!$B$2:$B$2001,A6) -> 5451.465 | F6: =IFERROR(E6/D6,0) -> 0.16988256 | G6: =IFERROR(E6/B6,0) -> 21.632798 | H6: =IFERROR(D6/B6,0) -> 127.33972 | I6: =IFERROR(AVERAGEIFS(Data!$H$2:$H$2001,Data!$B$2:$B$2001,A6),0) -> 23.998294 | J6: =IFERROR(AVERAGEIFS(Data!$M$2:$M$2001,Data!$B$2:$B$2001,A6),0) -> 16.321429 | K6: =IFERROR(SUMIFS(Data!$O$2:$O$2001,Data!$B$2:$B$2001,A6)/B6,0) -> 0.90079365 | L6: =RANK(B6,$B$5:$B$16) -> 2 | M6: =RANK(F6,$F$5:$F$16) -> 8 | N6: =M6-L6 -> 6 | O6: =IF(AND(L6<=4,M6>=7),"High volume, low margin",IF(AND(L6>=7,M6<=4),"Low volume, high margin","")) -> High volume, low margin
A7: MG | B7: =COUNTIFS(Data!$B$2:$B$2001,A7) -> 241 | C7: =B7/$B$17 -> 0.1205 | D7: =SUMIFS(Data!$P$2:$P$2001,Data!$B$2:$B$2001,A7) -> 31045.7 | E7: =SUMIFS(Data!$S$2:$S$2001,Data!$B$2:$B$2001,A7) -> 5486.7233 | F7: =IFERROR(E7/D7,0) -> 0.17673054 | G7: =IFERROR(E7/B7,0) -> 22.766487 | H7: =IFERROR(D7/B7,0) -> 128.82033 | I7: =IFERROR(AVERAGEIFS(Data!$H$2:$H$2001,Data!$B$2:$B$2001,A7),0) -> 23.306349 | J7: =IFERROR(AVERAGEIFS(Data!$M$2:$M$2001,Data!$B$2:$B$2001,A7),0) -> 12.539419 | K7: =IFERROR(SUMIFS(Data!$O$2:$O$2001,Data!$B$2:$B$2001,A7)/B7,0) -> 0.95850622 | L7: =RANK(B7,$B$5:$B$16) -> 3 | M7: =RANK(F7,$F$5:$F$16) -> 6 | N7: =M7-L7 -> 3 | O7: =IF(AND(L7<=4,M7>=7),"High volume, low margin",IF(AND(L7>=7,M7<=4),"Low volume, high margin",""))
A8: RS | B8: =COUNTIFS(Data!$B$2:$B$2001,A8) -> 110 | C8: =B8/$B$17 -> 0.055 | D8: =SUMIFS(Data!$P$2:$P$2001,Data!$B$2:$B$2001,A8) -> 15610.33 | E8: =SUMIFS(Data!$S$2:$S$2001,Data!$B$2:$B$2001,A8) -> 2729.7099 | F8: =IFERROR(E8/D8,0) -> 0.17486561 | G8: =IFERROR(E8/B8,0) -> 24.815545 | H8: =IFERROR(D8/B8,0) -> 141.91209 | I8: =IFERROR(AVERAGEIFS(Data!$H$2:$H$2001,Data!$B$2:$B$2001,A8),0) -> 24.362 | J8: =IFERROR(AVERAGEIFS(Data!$M$2:$M$2001,Data!$B$2:$B$2001,A8),0) -> 16.363636 | K8: =IFERROR(SUMIFS(Data!$O$2:$O$2001,Data!$B$2:$B$2001,A8)/B8,0) -> 0.87272727 | L8: =RANK(B8,$B$5:$B$16) -> 5 | M8: =RANK(F8,$F$5:$F$16) -> 7 | N8: =M8-L8 -> 2 | O8: =IF(AND(L8<=4,M8>=7),"High volume, low margin",IF(AND(L8>=7,M8<=4),"Low volume, high margin",""))
A9: PR | B9: =COUNTIFS(Data!$B$2:$B$2001,A9) -> 115 | C9: =B9/$B$17 -> 0.0575 | D9: =SUMIFS(Data!$P$2:$P$2001,Data!$B$2:$B$2001,A9) -> 16873.04 | E9: =SUMIFS(Data!$S$2:$S$2001,Data!$B$2:$B$2001,A9) -> 3163.2744 | F9: =IFERROR(E9/D9,0) -> 0.18747507 | G9: =IFERROR(E9/B9,0) -> 27.506734 | H9: =IFERROR(D9/B9,0) -> 146.72209 | I9: =IFERROR(AVERAGEIFS(Data!$H$2:$H$2001,Data!$B$2:$B$2001,A9),0) -> 23.454522 | J9: =IFERROR(AVERAGEIFS(Data!$M$2:$M$2001,Data!$B$2:$B$2001,A9),0) -> 13.165217 | K9: =IFERROR(SUMIFS(Data!$O$2:$O$2001,Data!$B$2:$B$2001,A9)/B9,0) -> 0.88695652 | L9: =RANK(B9,$B$5:$B$16) -> 4 | M9: =RANK(F9,$F$5:$F$16) -> 4 | N9: =M9-L9 -> 0 | O9: =IF(AND(L9<=4,M9>=7),"High volume, low margin",IF(AND(L9>=7,M9<=4),"Low volume, high margin",""))
A10: SC | B10: =COUNTIFS(Data!$B$2:$B$2001,A10) -> 96 | C10: =B10/$B$17 -> 0.048 | D10: =SUMIFS(Data!$P$2:$P$2001,Data!$B$2:$B$2001,A10) -> 13452.91 | E10: =SUMIFS(Data!$S$2:$S$2001,Data!$B$2:$B$2001,A10) -> 2562.6194 | F10: =IFERROR(E10/D10,0) -> 0.19048811 | G10: =IFERROR(E10/B10,0) -> 26.693952 | H10: =IFERROR(D10/B10,0) -> 140.13448 | I10: =IFERROR(AVERAGEIFS(Data!$H$2:$H$2001,Data!$B$2:$B$2001,A10),0) -> 24.139896 | J10: =IFERROR(AVERAGEIFS(Data!$M$2:$M$2001,Data!$B$2:$B$2001,A10),0) -> 14.791667 | K10: =IFERROR(SUMIFS(Data!$O$2:$O$2001,Data!$B$2:$B$2001,A10)/B10,0) -> 0.92708333 | L10: =RANK(B10,$B$5:$B$16) -> 6 | M10: =RANK(F10,$F$5:$F$16) -> 3 | N10: =M10-L10 -> -3 | O10: =IF(AND(L10<=4,M10>=7),"High volume, low margin",IF(AND(L10>=7,M10<=4),"Low volume, high margin",""))
A11: BA | B11: =COUNTIFS(Data!$B$2:$B$2001,A11) -> 65 | C11: =B11/$B$17 -> 0.0325 | D11: =SUMIFS(Data!$P$2:$P$2001,Data!$B$2:$B$2001,A11) -> 8267.86 | E11: =SUMIFS(Data!$S$2:$S$2001,Data!$B$2:$B$2001,A11) -> 937.0956 | F11: =IFERROR(E11/D11,0) -> 0.11334198 | G11: =IFERROR(E11/B11,0) -> 14.416855 | H11: =IFERROR(D11/B11,0) -> 127.19785 | I11: =IFERROR(AVERAGEIFS(Data!$H$2:$H$2001,Data!$B$2:$B$2001,A11),0) -> 32.066308 | J11: =IFERROR(AVERAGEIFS(Data!$M$2:$M$2001,Data!$B$2:$B$2001,A11),0) -> 20.230769 | K11: =IFERROR(SUMIFS(Data!$O$2:$O$2001,Data!$B$2:$B$2001,A11)/B11,0) -> 0.93846154 | L11: =RANK(B11,$B$5:$B$16) -> 7 | M11: =RANK(F11,$F$5:$F$16) -> 12 | N11: =M11-L11 -> 5 | O11: =IF(AND(L11<=4,M11>=7),"High volume, low margin",IF(AND(L11>=7,M11<=4),"Low volume, high margin",""))
A12: DF | B12: =COUNTIFS(Data!$B$2:$B$2001,A12) -> 52 | C12: =B12/$B$17 -> 0.026 | D12: =SUMIFS(Data!$P$2:$P$2001,Data!$B$2:$B$2001,A12) -> 7697.46 | E12: =SUMIFS(Data!$S$2:$S$2001,Data!$B$2:$B$2001,A12) -> 1537.265 | F12: =IFERROR(E12/D12,0) -> 0.19971068 | G12: =IFERROR(E12/B12,0) -> 29.562788 | H12: =IFERROR(D12/B12,0) -> 148.02808 | I12: =IFERROR(AVERAGEIFS(Data!$H$2:$H$2001,Data!$B$2:$B$2001,A12),0) -> 24.015769 | J12: =IFERROR(AVERAGEIFS(Data!$M$2:$M$2001,Data!$B$2:$B$2001,A12),0) -> 13.673077 | K12: =IFERROR(SUMIFS(Data!$O$2:$O$2001,Data!$B$2:$B$2001,A12)/B12,0) -> 0.96153846 | L12: =RANK(B12,$B$5:$B$16) -> 9 | M12: =RANK(F12,$F$5:$F$16) -> 2 | N12: =M12-L12 -> -7 | O12: =IF(AND(L12<=4,M12>=7),"High volume, low margin",IF(AND(L12>=7,M12<=4),"Low volume, high margin","")) -> Low volume, high margin
A13: GO | B13: =COUNTIFS(Data!$B$2:$B$2001,A13) -> 60 | C13: =B13/$B$17 -> 0.03 | D13: =SUMIFS(Data!$P$2:$P$2001,Data!$B$2:$B$2001,A13) -> 9527.25 | E13: =SUMIFS(Data!$S$2:$S$2001,Data!$B$2:$B$2001,A13) -> 1708.0977 | F13: =IFERROR(E13/D13,0) -> 0.17928549 | G13: =IFERROR(E13/B13,0) -> 28.468295 | H13: =IFERROR(D13/B13,0) -> 158.7875 | I13: =IFERROR(AVERAGEIFS(Data!$H$2:$H$2001,Data!$B$2:$B$2001,A13),0) -> 26.811667 | J13: =IFERROR(AVERAGEIFS(Data!$M$2:$M$2001,Data!$B$2:$B$2001,A13),0) -> 17.7 | K13: =IFERROR(SUMIFS(Data!$O$2:$O$2001,Data!$B$2:$B$2001,A13)/B13,0) -> 0.81666667 | L13: =RANK(B13,$B$5:$B$16) -> 8 | M13: =RANK(F13,$F$5:$F$16) -> 5 | N13: =M13-L13 -> -3 | O13: =IF(AND(L13<=4,M13>=7),"High volume, low margin",IF(AND(L13>=7,M13<=4),"Low volume, high margin",""))
A14: ES | B14: =COUNTIFS(Data!$B$2:$B$2001,A14) -> 33 | C14: =B14/$B$17 -> 0.0165 | D14: =SUMIFS(Data!$P$2:$P$2001,Data!$B$2:$B$2001,A14) -> 4059.07 | E14: =SUMIFS(Data!$S$2:$S$2001,Data!$B$2:$B$2001,A14) -> 680.598 | F14: =IFERROR(E14/D14,0) -> 0.16767338 | G14: =IFERROR(E14/B14,0) -> 20.624182 | H14: =IFERROR(D14/B14,0) -> 123.00212 | I14: =IFERROR(AVERAGEIFS(Data!$H$2:$H$2001,Data!$B$2:$B$2001,A14),0) -> 25.128182 | J14: =IFERROR(AVERAGEIFS(Data!$M$2:$M$2001,Data!$B$2:$B$2001,A14),0) -> 15.969697 | K14: =IFERROR(SUMIFS(Data!$O$2:$O$2001,Data!$B$2:$B$2001,A14)/B14,0) -> 0.84848485 | L14: =RANK(B14,$B$5:$B$16) -> 11 | M14: =RANK(F14,$F$5:$F$16) -> 9 | N14: =M14-L14 -> -2 | O14: =IF(AND(L14<=4,M14>=7),"High volume, low margin",IF(AND(L14>=7,M14<=4),"Low volume, high margin",""))
A15: PE | B15: =COUNTIFS(Data!$B$2:$B$2001,A15) -> 42 | C15: =B15/$B$17 -> 0.021 | D15: =SUMIFS(Data!$P$2:$P$2001,Data!$B$2:$B$2001,A15) -> 6527.81 | E15: =SUMIFS(Data!$S$2:$S$2001,Data!$B$2:$B$2001,A15) -> 787.2045 | F15: =IFERROR(E15/D15,0) -> 0.12059243 | G15: =IFERROR(E15/B15,0) -> 18.742964 | H15: =IFERROR(D15/B15,0) -> 155.42405 | I15: =IFERROR(AVERAGEIFS(Data!$H$2:$H$2001,Data!$B$2:$B$2001,A15),0) -> 37.270714 | J15: =IFERROR(AVERAGEIFS(Data!$M$2:$M$2001,Data!$B$2:$B$2001,A15),0) -> 23.5 | K15: =IFERROR(SUMIFS(Data!$O$2:$O$2001,Data!$B$2:$B$2001,A15)/B15,0) -> 0.9047619 | L15: =RANK(B15,$B$5:$B$16) -> 10 | M15: =RANK(F15,$F$5:$F$16) -> 11 | N15: =M15-L15 -> 1 | O15: =IF(AND(L15<=4,M15>=7),"High volume, low margin",IF(AND(L15>=7,M15<=4),"Low volume, high margin",""))
A16: CE | B16: =COUNTIFS(Data!$B$2:$B$2001,A16) -> 25 | C16: =B16/$B$17 -> 0.0125 | D16: =SUMIFS(Data!$P$2:$P$2001,Data!$B$2:$B$2001,A16) -> 4157.51 | E16: =SUMIFS(Data!$S$2:$S$2001,Data!$B$2:$B$2001,A16) -> 561.9106 | F16: =IFERROR(E16/D16,0) -> 0.13515556 | G16: =IFERROR(E16/B16,0) -> 22.476424 | H16: =IFERROR(D16/B16,0) -> 166.3004 | I16: =IFERROR(AVERAGEIFS(Data!$H$2:$H$2001,Data!$B$2:$B$2001,A16),0) -> 40.014 | J16: =IFERROR(AVERAGEIFS(Data!$M$2:$M$2001,Data!$B$2:$B$2001,A16),0) -> 22.4 | K16: =IFERROR(SUMIFS(Data!$O$2:$O$2001,Data!$B$2:$B$2001,A16)/B16,0) -> 0.96 | L16: =RANK(B16,$B$5:$B$16) -> 12 | M16: =RANK(F16,$F$5:$F$16) -> 10 | N16: =M16-L16 -> -2 | O16: =IF(AND(L16<=4,M16>=7),"High volume, low margin",IF(AND(L16>=7,M16<=4),"Low volume, high margin",""))
A17: Total / Avg | B17: =SUM(B5:B16) -> 2000 | C17: =SUM(C5:C16) -> 1 | D17: =SUM(D5:D16) -> 264925.66 | E17: =SUM(E5:E16) -> 50856.568 | F17: =E17/D17 -> 0.19196543 | G17: =E17/B17 -> 25.428284 | H17: =D17/B17 -> 132.46283 | I17: =AVERAGE(Data!$H$2:$H$2001) -> 21.948125 | J17: =AVERAGE(Data!$M$2:$M$2001) -> 12.45 | K17: =SUM(Data!$O$2:$O$2001)/B17 -> 0.9275
A19: Rank Gap = Margin Rank - Volume Rank. A large positive gap means high order volume but weak profitability.

Sheet Monthly Trend
A1: Monthly Sales Trend
A2: Month list uses EDATE; moving average, MoM growth and cumulative revenue are formulas.
A4: Month | B4: Orders | C4: Revenue | D4: Net Profit | E4: Profit Margin | F4: MoM Order Growth | G4: 3-Mo Moving Avg Orders | H4: Cumulative Revenue | I4: Avg Delivery Days | J4: Flag
A5: 42736 | B5: =COUNTIFS(Data!$L$2:$L$2001,A5) -> 19 | C5: =SUMIFS(Data!$P$2:$P$2001,Data!$L$2:$L$2001,A5) -> 2172.54 | D5: =SUMIFS(Data!$S$2:$S$2001,Data!$L$2:$L$2001,A5) -> 430.0502 | E5: =IFERROR(D5/C5,0) -> 0.19794812 | F5: ="" | G5: ="" | H5: =SUM($C$5:C5) -> 2172.54 | I5: =IFERROR(AVERAGEIFS(Data!$M$2:$M$2001,Data!$L$2:$L$2001,A5),0) -> 12.315789 | J5: =IF(B5=MAX($B$5:$B$24),"Peak month",IF(B5=MIN($B$5:$B$24),"Lowest month","")) -> Lowest month
A6: =EDATE(A5,1) -> 42767 | B6: =COUNTIFS(Data!$L$2:$L$2001,A6) -> 32 | C6: =SUMIFS(Data!$P$2:$P$2001,Data!$L$2:$L$2001,A6) -> 3758.18 | D6: =SUMIFS(Data!$S$2:$S$2001,Data!$L$2:$L$2001,A6) -> 625.6623 | E6: =IFERROR(D6/C6,0) -> 0.16648013 | F6: =IFERROR(B6/B5-1,"") -> 0.68421053 | G6: ="" | H6: =SUM($C$5:C6) -> 5930.72 | I6: =IFERROR(AVERAGEIFS(Data!$M$2:$M$2001,Data!$L$2:$L$2001,A6),0) -> 11.59375 | J6: =IF(B6=MAX($B$5:$B$24),"Peak month",IF(B6=MIN($B$5:$B$24),"Lowest month",""))
A7: =EDATE(A6,1) -> 42795 | B7: =COUNTIFS(Data!$L$2:$L$2001,A7) -> 23 | C7: =SUMIFS(Data!$P$2:$P$2001,Data!$L$2:$L$2001,A7) -> 2771.36 | D7: =SUMIFS(Data!$S$2:$S$2001,Data!$L$2:$L$2001,A7) -> 497.0758 | E7: =IFERROR(D7/C7,0) -> 0.17936169 | F7: =IFERROR(B7/B6-1,"") -> -0.28125 | G7: =AVERAGE(B5:B7) -> 24.666667 | H7: =SUM($C$5:C7) -> 8702.08 | I7: =IFERROR(AVERAGEIFS(Data!$M$2:$M$2001,Data!$L$2:$L$2001,A7),0) -> 11.652174 | J7: =IF(B7=MAX($B$5:$B$24),"Peak month",IF(B7=MIN($B$5:$B$24),"Lowest month",""))
A8: =EDATE(A7,1) -> 42826 | B8: =COUNTIFS(Data!$L$2:$L$2001,A8) -> 50 | C8: =SUMIFS(Data!$P$2:$P$2001,Data!$L$2:$L$2001,A8) -> 6716.63 | D8: =SUMIFS(Data!$S$2:$S$2001,Data!$L$2:$L$2001,A8) -> 1223.0632 | E8: =IFERROR(D8/C8,0) -> 0.18209477 | F8: =IFERROR(B8/B7-1,"") -> 1.173913 | G8: =AVERAGE(B6:B8) -> 35 | H8: =SUM($C$5:C8) -> 15418.71 | I8: =IFERROR(AVERAGEIFS(Data!$M$2:$M$2001,Data!$L$2:$L$2001,A8),0) -> 12.06 | J8: =IF(B8=MAX($B$5:$B$24),"Peak month",IF(B8=MIN($B$5:$B$24),"Lowest month",""))
A9: =EDATE(A8,1) -> 42856 | B9: =COUNTIFS(Data!$L$2:$L$2001,A9) -> 50 | C9: =SUMIFS(Data!$P$2:$P$2001,Data!$L$2:$L$2001,A9) -> 6607.42 | D9: =SUMIFS(Data!$S$2:$S$2001,Data!$L$2:$L$2001,A9) -> 1236.3609 | E9: =IFERROR(D9/C9,0) -> 0.18711704 | F9: =IFERROR(B9/B8-1,"") -> 0 | G9: =AVERAGE(B7:B9) -> 41 | H9: =SUM($C$5:C9) -> 22026.13 | I9: =IFERROR(AVERAGEIFS(Data!$M$2:$M$2001,Data!$L$2:$L$2001,A9),0) -> 14.08 | J9: =IF(B9=MAX($B$5:$B$24),"Peak month",IF(B9=MIN($B$5:$B$24),"Lowest month",""))
A10: =EDATE(A9,1) -> 42887 | B10: =COUNTIFS(Data!$L$2:$L$2001,A10) -> 62 | C10: =SUMIFS(Data!$P$2:$P$2001,Data!$L$2:$L$2001,A10) -> 7950.55 | D10: =SUMIFS(Data!$S$2:$S$2001,Data!$L$2:$L$2001,A10) -> 1494.4801 | E10: =IFERROR(D10/C10,0) -> 0.18797191 | F10: =IFERROR(B10/B9-1,"") -> 0.24 | G10: =AVERAGE(B8:B10) -> 54 | H10: =SUM($C$5:C10) -> 29976.68 | I10: =IFERROR(AVERAGEIFS(Data!$M$2:$M$2001,Data!$L$2:$L$2001,A10),0) -> 11.741935 | J10: =IF(B10=MAX($B$5:$B$24),"Peak month",IF(B10=MIN($B$5:$B$24),"Lowest month",""))
A11: =EDATE(A10,1) -> 42917 | B11: =COUNTIFS(Data!$L$2:$L$2001,A11) -> 86 | C11: =SUMIFS(Data!$P$2:$P$2001,Data!$L$2:$L$2001,A11) -> 11224.26 | D11: =SUMIFS(Data!$S$2:$S$2001,Data!$L$2:$L$2001,A11) -> 2302.3632 | E11: =IFERROR(D11/C11,0) -> 0.20512383 | F11: =IFERROR(B11/B10-1,"") -> 0.38709677 | G11: =AVERAGE(B9:B11) -> 66 | H11: =SUM($C$5:C11) -> 41200.94 | I11: =IFERROR(AVERAGEIFS(Data!$M$2:$M$2001,Data!$L$2:$L$2001,A11),0) -> 12.44186 | J11: =IF(B11=MAX($B$5:$B$24),"Peak month",IF(B11=MIN($B$5:$B$24),"Lowest month",""))
A12: =EDATE(A11,1) -> 42948 | B12: =COUNTIFS(Data!$L$2:$L$2001,A12) -> 94 | C12: =SUMIFS(Data!$P$2:$P$2001,Data!$L$2:$L$2001,A12) -> 11209.59 | D12: =SUMIFS(Data!$S$2:$S$2001,Data!$L$2:$L$2001,A12) -> 1998.6299 | E12: =IFERROR(D12/C12,0) -> 0.17829643 | F12: =IFERROR(B12/B11-1,"") -> 0.093023256 | G12: =AVERAGE(B10:B12) -> 80.666667 | H12: =SUM($C$5:C12) -> 52410.53 | I12: =IFERROR(AVERAGEIFS(Data!$M$2:$M$2001,Data!$L$2:$L$2001,A12),0) -> 11.851064 | J12: =IF(B12=MAX($B$5:$B$24),"Peak month",IF(B12=MIN($B$5:$B$24),"Lowest month",""))
A13: =EDATE(A12,1) -> 42979 | B13: =COUNTIFS(Data!$L$2:$L$2001,A13) -> 76 | C13: =SUMIFS(Data!$P$2:$P$2001,Data!$L$2:$L$2001,A13) -> 9815 | D13: =SUMIFS(Data!$S$2:$S$2001,Data!$L$2:$L$2001,A13) -> 1868.7309 | E13: =IFERROR(D13/C13,0) -> 0.1903954 | F13: =IFERROR(B13/B12-1,"") -> -0.19148936 | G13: =AVERAGE(B11:B13) -> 85.333333 | H13: =SUM($C$5:C13) -> 62225.53 | I13: =IFERROR(AVERAGEIFS(Data!$M$2:$M$2001,Data!$L$2:$L$2001,A13),0) -> 13.052632 | J13: =IF(B13=MAX($B$5:$B$24),"Peak month",IF(B13=MIN($B$5:$B$24),"Lowest month",""))
A14: =EDATE(A13,1) -> 43009 | B14: =COUNTIFS(Data!$L$2:$L$2001,A14) -> 93 | C14: =SUMIFS(Data!$P$2:$P$2001,Data!$L$2:$L$2001,A14) -> 12961.28 | D14: =SUMIFS(Data!$S$2:$S$2001,Data!$L$2:$L$2001,A14) -> 2459.5793 | E14: =IFERROR(D14/C14,0) -> 0.18976361 | F14: =IFERROR(B14/B13-1,"") -> 0.22368421 | G14: =AVERAGE(B12:B14) -> 87.666667 | H14: =SUM($C$5:C14) -> 75186.81 | I14: =IFERROR(AVERAGEIFS(Data!$M$2:$M$2001,Data!$L$2:$L$2001,A14),0) -> 13.483871 | J14: =IF(B14=MAX($B$5:$B$24),"Peak month",IF(B14=MIN($B$5:$B$24),"Lowest month",""))
A15: =EDATE(A14,1) -> 43040 | B15: =COUNTIFS(Data!$L$2:$L$2001,A15) -> 162 | C15: =SUMIFS(Data!$P$2:$P$2001,Data!$L$2:$L$2001,A15) -> 22385.65 | D15: =SUMIFS(Data!$S$2:$S$2001,Data!$L$2:$L$2001,A15) -> 4342.0319 | E15: =IFERROR(D15/C15,0) -> 0.19396497 | F15: =IFERROR(B15/B14-1,"") -> 0.74193548 | G15: =AVERAGE(B13:B15) -> 110.33333 | H15: =SUM($C$5:C15) -> 97572.46 | I15: =IFERROR(AVERAGEIFS(Data!$M$2:$M$2001,Data!$L$2:$L$2001,A15),0) -> 12.246914 | J15: =IF(B15=MAX($B$5:$B$24),"Peak month",IF(B15=MIN($B$5:$B$24),"Lowest month",""))
A16: =EDATE(A15,1) -> 43070 | B16: =COUNTIFS(Data!$L$2:$L$2001,A16) -> 130 | C16: =SUMIFS(Data!$P$2:$P$2001,Data!$L$2:$L$2001,A16) -> 17841.41 | D16: =SUMIFS(Data!$S$2:$S$2001,Data!$L$2:$L$2001,A16) -> 3479.1945 | E16: =IFERROR(D16/C16,0) -> 0.1950067 | F16: =IFERROR(B16/B15-1,"") -> -0.19753086 | G16: =AVERAGE(B14:B16) -> 128.33333 | H16: =SUM($C$5:C16) -> 115413.87 | I16: =IFERROR(AVERAGEIFS(Data!$M$2:$M$2001,Data!$L$2:$L$2001,A16),0) -> 13.284615 | J16: =IF(B16=MAX($B$5:$B$24),"Peak month",IF(B16=MIN($B$5:$B$24),"Lowest month",""))
A17: =EDATE(A16,1) -> 43101 | B17: =COUNTIFS(Data!$L$2:$L$2001,A17) -> 110 | C17: =SUMIFS(Data!$P$2:$P$2001,Data!$L$2:$L$2001,A17) -> 14582.56 | D17: =SUMIFS(Data!$S$2:$S$2001,Data!$L$2:$L$2001,A17) -> 2686.1614 | E17: =IFERROR(D17/C17,0) -> 0.18420369 | F17: =IFERROR(B17/B16-1,"") -> -0.15384615 | G17: =AVERAGE(B15:B17) -> 134 | H17: =SUM($C$5:C17) -> 129996.43 | I17: =IFERROR(AVERAGEIFS(Data!$M$2:$M$2001,Data!$L$2:$L$2001,A17),0) -> 12.136364 | J17: =IF(B17=MAX($B$5:$B$24),"Peak month",IF(B17=MIN($B$5:$B$24),"Lowest month",""))
A18: =EDATE(A17,1) -> 43132 | B18: =COUNTIFS(Data!$L$2:$L$2001,A18) -> 118 | C18: =SUMIFS(Data!$P$2:$P$2001,Data!$L$2:$L$2001,A18) -> 15315.65 | D18: =SUMIFS(Data!$S$2:$S$2001,Data!$L$2:$L$2001,A18) -> 2961.8738 | E18: =IFERROR(D18/C18,0) -> 0.19338871 | F18: =IFERROR(B18/B17-1,"") -> 0.072727273 | G18: =AVERAGE(B16:B18) -> 119.33333 | H18: =SUM($C$5:C18) -> 145312.08 | I18: =IFERROR(AVERAGEIFS(Data!$M$2:$M$2001,Data!$L$2:$L$2001,A18),0) -> 12.237288 | J18: =IF(B18=MAX($B$5:$B$24),"Peak month",IF(B18=MIN($B$5:$B$24),"Lowest month",""))
... A24: =EDATE(A23,1) -> 43313 | B24: =COUNTIFS(Data!$L$2:$L$2001,A24) -> 188 | C24: =SUMIFS(Data!$P$2:$P$2001,Data!$L$2:$L$2001,A24) -> 25620.95 | D24: =SUMIFS(Data!$S$2:$S$2001,Data!$L$2:$L$2001,A24) -> 5071.6196 | E24: =IFERROR(D24/C24,0) -> 0.19794815 | F24: =IFERROR(B24/B23-1,"") -> 0.21290323 | G24: =AVERAGE(B22:B24) -> 167.33333 | H24: =SUM($C$5:C24) -> 264925.66 | I24: =IFERROR(AVERAGEIFS(Data!$M$2:$M$2001,Data!$L$2:$L$2001,A24),0) -> 12.090426 | J24: =IF(B24=MAX($B$5:$B$24),"Peak month",IF(B24=MIN($B$5:$B$24),"Lowest month","")) -> Peak month

Sheet Delivery Analysis
A1: Delivery Performance Analysis
A2: Section 1: delivery-time buckets. Section 2: on-time vs late. Section 3: bottleneck states.
A4: Delivery Time Bucket | B4: Orders | C4: Share of Orders | D4: Avg Review Score | E4: Avg Profit / Order | F4: Late %
A5: 0-7 days | B5: =COUNTIFS(Data!$T$2:$T$2001,A5) -> 468 | C5: =B5/SUM($B$5:$B$8) -> 0.234 | D5: =IFERROR(AVERAGEIFS(Data!$J$2:$J$2001,Data!$T$2:$T$2001,A5),0) -> 4.4230769 | E5: =IFERROR(AVERAGEIFS(Data!$S$2:$S$2001,Data!$T$2:$T$2001,A5),0) -> 24.816348 | F5: =IFERROR(1-SUMIFS(Data!$O$2:$O$2001,Data!$T$2:$T$2001,A5)/B5,0) -> 0
A6: 8-14 days | B6: =COUNTIFS(Data!$T$2:$T$2001,A6) -> 949 | C6: =B6/SUM($B$5:$B$8) -> 0.4745 | D6: =IFERROR(AVERAGEIFS(Data!$J$2:$J$2001,Data!$T$2:$T$2001,A6),0) -> 4.3877766 | E6: =IFERROR(AVERAGEIFS(Data!$S$2:$S$2001,Data!$T$2:$T$2001,A6),0) -> 26.407715 | F6: =IFERROR(1-SUMIFS(Data!$O$2:$O$2001,Data!$T$2:$T$2001,A6)/B6,0) -> 0.01369863
A7: 15-21 days | B7: =COUNTIFS(Data!$T$2:$T$2001,A7) -> 404 | C7: =B7/SUM($B$5:$B$8) -> 0.202 | D7: =IFERROR(AVERAGEIFS(Data!$J$2:$J$2001,Data!$T$2:$T$2001,A7),0) -> 4.0420792 | E7: =IFERROR(AVERAGEIFS(Data!$S$2:$S$2001,Data!$T$2:$T$2001,A7),0) -> 23.695877 | F7: =IFERROR(1-SUMIFS(Data!$O$2:$O$2001,Data!$T$2:$T$2001,A7)/B7,0) -> 0.089108911
A8: 22+ days | B8: =COUNTIFS(Data!$T$2:$T$2001,A8) -> 179 | C8: =B8/SUM($B$5:$B$8) -> 0.0895 | D8: =IFERROR(AVERAGEIFS(Data!$J$2:$J$2001,Data!$T$2:$T$2001,A8),0) -> 3.1396648 | E8: =IFERROR(AVERAGEIFS(Data!$S$2:$S$2001,Data!$T$2:$T$2001,A8),0) -> 25.745595 | F8: =IFERROR(1-SUMIFS(Data!$O$2:$O$2001,Data!$T$2:$T$2001,A8)/B8,0) -> 0.53631285
A11: Delivery Status | B11: Orders | C11: Share of Orders | D11: Avg Review Score | E11: Avg Profit / Order | F11: Avg Delay (days)
A12: On-time | B12: =COUNTIFS(Data!$O$2:$O$2001,1) -> 1855 | C12: =B12/SUM($B$12:$B$13) -> 0.9275 | D12: =IFERROR(AVERAGEIFS(Data!$J$2:$J$2001,Data!$O$2:$O$2001,1),0) -> 4.3358491 | E12: =IFERROR(AVERAGEIFS(Data!$S$2:$S$2001,Data!$O$2:$O$2001,1),0) -> 25.217932 | F12: =IFERROR(AVERAGEIFS(Data!$N$2:$N$2001,Data!$O$2:$O$2001,1),0) -> 0
A13: Late | B13: =COUNTIFS(Data!$O$2:$O$2001,0) -> 145 | C13: =B13/SUM($B$12:$B$13) -> 0.0725 | D13: =IFERROR(AVERAGEIFS(Data!$J$2:$J$2001,Data!$O$2:$O$2001,0),0) -> 2.662069 | E13: =IFERROR(AVERAGEIFS(Data!$S$2:$S$2001,Data!$O$2:$O$2001,0),0) -> 28.119342 | F13: =IFERROR(AVERAGEIFS(Data!$N$2:$N$2001,Data!$O$2:$O$2001,0),0) -> 4.8827586
A14: Review score drop when late | D14: =D12-D13 -> 1.6737801
A17: State | B17: Avg Delivery Days | C17: On-Time % | D17: Avg Delay of Late Orders | E17: Avg Review Score | F17: Bottleneck Rating
A18: SP | B18: =IFERROR(AVERAGEIFS(Data!$M$2:$M$2001,Data!$B$2:$B$2001,A18),0) -> 8.6567657 | C18: =IFERROR(SUMIFS(Data!$O$2:$O$2001,Data!$B$2:$B$2001,A18)/COUNTIFS(Data!$B$2:$B$2001,A18),0) -> 0.94609461 | D18: =IFERROR(AVERAGEIFS(Data!$N$2:$N$2001,Data!$B$2:$B$2001,A18,Data!$O$2:$O$2001,0),0) -> 3.4285714 | E18: =IFERROR(AVERAGEIFS(Data!$J$2:$J$2001,Data!$B$2:$B$2001,A18),0) -> 4.3421342 | F18: =IF(B18>=$B$30*1.25,"High",IF(B18>=$B$30,"Medium","Low")) -> Low
A19: RJ | B19: =IFERROR(AVERAGEIFS(Data!$M$2:$M$2001,Data!$B$2:$B$2001,A19),0) -> 16.321429 | C19: =IFERROR(SUMIFS(Data!$O$2:$O$2001,Data!$B$2:$B$2001,A19)/COUNTIFS(Data!$B$2:$B$2001,A19),0) -> 0.90079365 | D19: =IFERROR(AVERAGEIFS(Data!$N$2:$N$2001,Data!$B$2:$B$2001,A19,Data!$O$2:$O$2001,0),0) -> 5.84 | E19: =IFERROR(AVERAGEIFS(Data!$J$2:$J$2001,Data!$B$2:$B$2001,A19),0) -> 4.0079365 | F19: =IF(B19>=$B$30*1.25,"High",IF(B19>=$B$30,"Medium","Low")) -> High
A20: MG | B20: =IFERROR(AVERAGEIFS(Data!$M$2:$M$2001,Data!$B$2:$B$2001,A20),0) -> 12.539419 | C20: =IFERROR(SUMIFS(Data!$O$2:$O$2001,Data!$B$2:$B$2001,A20)/COUNTIFS(Data!$B$2:$B$2001,A20),0) -> 0.95850622 | D20: =IFERROR(AVERAGEIFS(Data!$N$2:$N$2001,Data!$B$2:$B$2001,A20,Data!$O$2:$O$2001,0),0) -> 4.4 | E20: =IFERROR(AVERAGEIFS(Data!$J$2:$J$2001,Data!$B$2:$B$2001,A20),0) -> 4.3526971 | F20: =IF(B20>=$B$30*1.25,"High",IF(B20>=$B$30,"Medium","Low")) -> Medium
A21: RS | B21: =IFERROR(AVERAGEIFS(Data!$M$2:$M$2001,Data!$B$2:$B$2001,A21),0) -> 16.363636 | C21: =IFERROR(SUMIFS(Data!$O$2:$O$2001,Data!$B$2:$B$2001,A21)/COUNTIFS(Data!$B$2:$B$2001,A21),0) -> 0.87272727 | D21: =IFERROR(AVERAGEIFS(Data!$N$2:$N$2001,Data!$B$2:$B$2001,A21,Data!$O$2:$O$2001,0),0) -> 5.8571429 | E21: =IFERROR(AVERAGEIFS(Data!$J$2:$J$2001,Data!$B$2:$B$2001,A21),0) -> 3.8909091 | F21: =IF(B21>=$B$30*1.25,"High",IF(B21>=$B$30,"Medium","Low")) -> High
A22: PR | B22: =IFERROR(AVERAGEIFS(Data!$M$2:$M$2001,Data!$B$2:$B$2001,A22),0) -> 13.165217 | C22: =IFERROR(SUMIFS(Data!$O$2:$O$2001,Data!$B$2:$B$2001,A22)/COUNTIFS(Data!$B$2:$B$2001,A22),0) -> 0.88695652 | D22: =IFERROR(AVERAGEIFS(Data!$N$2:$N$2001,Data!$B$2:$B$2001,A22,Data!$O$2:$O$2001,0),0) -> 3.9230769 | E22: =IFERROR(AVERAGEIFS(Data!$J$2:$J$2001,Data!$B$2:$B$2001,A22),0) -> 4.226087 | F22: =IF(B22>=$B$30*1.25,"High",IF(B22>=$B$30,"Medium","Low")) -> Medium
A23: SC | B23: =IFERROR(AVERAGEIFS(Data!$M$2:$M$2001,Data!$B$2:$B$2001,A23),0) -> 14.791667 | C23: =IFERROR(SUMIFS(Data!$O$2:$O$2001,Data!$B$2:$B$2001,A23)/COUNTIFS(Data!$B$2:$B$2001,A23),0) -> 0.92708333 | D23: =IFERROR(AVERAGEIFS(Data!$N$2:$N$2001,Data!$B$2:$B$2001,A23,Data!$O$2:$O$2001,0),0) -> 4.5714286 | E23: =IFERROR(AVERAGEIFS(Data!$J$2:$J$2001,Data!$B$2:$B$2001,A23),0) -> 4.15625 | F23: =IF(B23>=$B$30*1.25,"High",IF(B23>=$B$30,"Medium","Low")) -> Medium
A24: BA | B24: =IFERROR(AVERAGEIFS(Data!$M$2:$M$2001,Data!$B$2:$B$2001,A24),0) -> 20.230769 | C24: =IFERROR(SUMIFS(Data!$O$2:$O$2001,Data!$B$2:$B$2001,A24)/COUNTIFS(Data!$B$2:$B$2001,A24),0) -> 0.93846154 | D24: =IFERROR(AVERAGEIFS(Data!$N$2:$N$2001,Data!$B$2:$B$2001,A24,Data!$O$2:$O$2001,0),0) -> 6.5 | E24: =IFERROR(AVERAGEIFS(Data!$J$2:$J$2001,Data!$B$2:$B$2001,A24),0) -> 3.9076923 | F24: =IF(B24>=$B$30*1.25,"High",IF(B24>=$B$30,"Medium","Low")) -> High
A25: DF | B25: =IFERROR(AVERAGEIFS(Data!$M$2:$M$2001,Data!$B$2:$B$2001,A25),0) -> 13.673077 | C25: =IFERROR(SUMIFS(Data!$O$2:$O$2001,Data!$B$2:$B$2001,A25)/COUNTIFS(Data!$B$2:$B$2001,A25),0) -> 0.96153846 | D25: =IFERROR(AVERAGEIFS(Data!$N$2:$N$2001,Data!$B$2:$B$2001,A25,Data!$O$2:$O$2001,0),0) -> 2 | E25: =IFERROR(AVERAGEIFS(Data!$J$2:$J$2001,Data!$B$2:$B$2001,A25),0) -> 4.3269231 | F25: =IF(B25>=$B$30*1.25,"High",IF(B25>=$B$30,"Medium","Low")) -> Medium
A26: GO | B26: =IFERROR(AVERAGEIFS(Data!$M$2:$M$2001,Data!$B$2:$B$2001,A26),0) -> 17.7 | C26: =IFERROR(SUMIFS(Data!$O$2:$O$2001,Data!$B$2:$B$2001,A26)/COUNTIFS(Data!$B$2:$B$2001,A26),0) -> 0.81666667 | D26: =IFERROR(AVERAGEIFS(Data!$N$2:$N$2001,Data!$B$2:$B$2001,A26,Data!$O$2:$O$2001,0),0) -> 6.8181818 | E26: =IFERROR(AVERAGEIFS(Data!$J$2:$J$2001,Data!$B$2:$B$2001,A26),0) -> 3.95 | F26: =IF(B26>=$B$30*1.25,"High",IF(B26>=$B$30,"Medium","Low")) -> High
A27: ES | B27: =IFERROR(AVERAGEIFS(Data!$M$2:$M$2001,Data!$B$2:$B$2001,A27),0) -> 15.969697 | C27: =IFERROR(SUMIFS(Data!$O$2:$O$2001,Data!$B$2:$B$2001,A27)/COUNTIFS(Data!$B$2:$B$2001,A27),0) -> 0.84848485 | D27: =IFERROR(AVERAGEIFS(Data!$N$2:$N$2001,Data!$B$2:$B$2001,A27,Data!$O$2:$O$2001,0),0) -> 4.4 | E27: =IFERROR(AVERAGEIFS(Data!$J$2:$J$2001,Data!$B$2:$B$2001,A27),0) -> 4 | F27: =IF(B27>=$B$30*1.25,"High",IF(B27>=$B$30,"Medium","Low")) -> High
A28: PE | B28: =IFERROR(AVERAGEIFS(Data!$M$2:$M$2001,Data!$B$2:$B$2001,A28),0) -> 23.5 | C28: =IFERROR(SUMIFS(Data!$O$2:$O$2001,Data!$B$2:$B$2001,A28)/COUNTIFS(Data!$B$2:$B$2001,A28),0) -> 0.9047619 | D28: =IFERROR(AVERAGEIFS(Data!$N$2:$N$2001,Data!$B$2:$B$2001,A28,Data!$O$2:$O$2001,0),0) -> 14.25 | E28: =IFERROR(AVERAGEIFS(Data!$J$2:$J$2001,Data!$B$2:$B$2001,A28),0) -> 3.8571429 | F28: =IF(B28>=$B$30*1.25,"High",IF(B28>=$B$30,"Medium","Low")) -> High
A29: CE | B29: =IFERROR(AVERAGEIFS(Data!$M$2:$M$2001,Data!$B$2:$B$2001,A29),0) -> 22.4 | C29: =IFERROR(SUMIFS(Data!$O$2:$O$2001,Data!$B$2:$B$2001,A29)/COUNTIFS(Data!$B$2:$B$2001,A29),0) -> 0.96 | D29: =IFERROR(AVERAGEIFS(Data!$N$2:$N$2001,Data!$B$2:$B$2001,A29,Data!$O$2:$O$2001,0),0) -> 1 | E29: =IFERROR(AVERAGEIFS(Data!$J$2:$J$2001,Data!$B$2:$B$2001,A29),0) -> 4 | F29: =IF(B29>=$B$30*1.25,"High",IF(B29>=$B$30,"Medium","Low")) -> High
A30: All-state average | B30: =AVERAGE(Data!$M$2:$M$2001) -> 12.45
A31: Bottleneck rating: High = avg delivery time 25%+ above the overall average; Medium = above average.

Sheet Category Analysis
A1: Product Category Analysis
A2: Cost ratios are pulled from the Assumptions sheet with INDEX/MATCH.
A4: Category | B4: Orders | C4: Revenue | D4: Net Profit | E4: Profit Margin | F4: Avg Price | G4: Avg Review | H4: Cost Ratio | I4: Profit Rank
A5: bed_bath_table | B5: =COUNTIFS(Data!$F$2:$F$2001,A5) -> 353 | C5: =SUMIFS(Data!$P$2:$P$2001,Data!$F$2:$F$2001,A5) -> 40417.9 | D5: =SUMIFS(Data!$S$2:$S$2001,Data!$F$2:$F$2001,A5) -> 8067.847 | E5: =IFERROR(D5/C5,0) -> 0.19961074 | F5: =IFERROR(AVERAGEIFS(Data!$G$2:$G$2001,Data!$F$2:$F$2001,A5),0) -> 93.422521 | G5: =IFERROR(AVERAGEIFS(Data!$J$2:$J$2001,Data!$F$2:$F$2001,A5),0) -> 4.266289 | H5: =INDEX(Assumptions!$B$8:$B$16,MATCH(A5,Assumptions!$A$8:$A$16,0)) -> 0.62 | I5: =RANK(D5,$D$5:$D$13) -> 2
A6: health_beauty | B6: =COUNTIFS(Data!$F$2:$F$2001,A6) -> 296 | C6: =SUMIFS(Data!$P$2:$P$2001,Data!$F$2:$F$2001,A6) -> 35451.86 | D6: =SUMIFS(Data!$S$2:$S$2001,Data!$F$2:$F$2001,A6) -> 8255.589 | E6: =IFERROR(D6/C6,0) -> 0.23286758 | F6: =IFERROR(AVERAGEIFS(Data!$G$2:$G$2001,Data!$F$2:$F$2001,A6),0) -> 97.796453 | G6: =IFERROR(AVERAGEIFS(Data!$J$2:$J$2001,Data!$F$2:$F$2001,A6),0) -> 4.1824324 | H6: =INDEX(Assumptions!$B$8:$B$16,MATCH(A6,Assumptions!$A$8:$A$16,0)) -> 0.58 | I6: =RANK(D6,$D$5:$D$13) -> 1
A7: sports_leisure | B7: =COUNTIFS(Data!$F$2:$F$2001,A7) -> 248 | C7: =SUMIFS(Data!$P$2:$P$2001,Data!$F$2:$F$2001,A7) -> 31386.84 | D7: =SUMIFS(Data!$S$2:$S$2001,Data!$F$2:$F$2001,A7) -> 6050.9328 | E7: =IFERROR(D7/C7,0) -> 0.19278566 | F7: =IFERROR(AVERAGEIFS(Data!$G$2:$G$2001,Data!$F$2:$F$2001,A7),0) -> 104.51544 | G7: =IFERROR(AVERAGEIFS(Data!$J$2:$J$2001,Data!$F$2:$F$2001,A7),0) -> 4.2459677 | H7: =INDEX(Assumptions!$B$8:$B$16,MATCH(A7,Assumptions!$A$8:$A$16,0)) -> 0.64 | I7: =RANK(D7,$D$5:$D$13) -> 4
A8: furniture_decor | B8: =COUNTIFS(Data!$F$2:$F$2001,A8) -> 218 | C8: =SUMIFS(Data!$P$2:$P$2001,Data!$F$2:$F$2001,A8) -> 29964.94 | D8: =SUMIFS(Data!$S$2:$S$2001,Data!$F$2:$F$2001,A8) -> 4792.062 | E8: =IFERROR(D8/C8,0) -> 0.1599223 | F8: =IFERROR(AVERAGEIFS(Data!$G$2:$G$2001,Data!$F$2:$F$2001,A8),0) -> 116.06028 | G8: =IFERROR(AVERAGEIFS(Data!$J$2:$J$2001,Data!$F$2:$F$2001,A8),0) -> 4.1788991 | H8: =INDEX(Assumptions!$B$8:$B$16,MATCH(A8,Assumptions!$A$8:$A$16,0)) -> 0.7 | I8: =RANK(D8,$D$5:$D$13) -> 5
A9: computers_accessories | B9: =COUNTIFS(Data!$F$2:$F$2001,A9) -> 203 | C9: =SUMIFS(Data!$P$2:$P$2001,Data!$F$2:$F$2001,A9) -> 33621.59 | D9: =SUMIFS(Data!$S$2:$S$2001,Data!$F$2:$F$2001,A9) -> 4712.7456 | E9: =IFERROR(D9/C9,0) -> 0.14017022 | F9: =IFERROR(AVERAGEIFS(Data!$G$2:$G$2001,Data!$F$2:$F$2001,A9),0) -> 142.54611 | G9: =IFERROR(AVERAGEIFS(Data!$J$2:$J$2001,Data!$F$2:$F$2001,A9),0) -> 4.1724138 | H9: =INDEX(Assumptions!$B$8:$B$16,MATCH(A9,Assumptions!$A$8:$A$16,0)) -> 0.74 | I9: =RANK(D9,$D$5:$D$13) -> 6
A10: watches_gifts | B10: =COUNTIFS(Data!$F$2:$F$2001,A10) -> 188 | C10: =SUMIFS(Data!$P$2:$P$2001,Data!$F$2:$F$2001,A10) -> 35149.83 | D10: =SUMIFS(Data!$S$2:$S$2001,Data!$F$2:$F$2001,A10) -> 7898.7432 | E10: =IFERROR(D10/C10,0) -> 0.2247164 | F10: =IFERROR(AVERAGEIFS(Data!$G$2:$G$2001,Data!$F$2:$F$2001,A10),0) -> 164.03713 | G10: =IFERROR(AVERAGEIFS(Data!$J$2:$J$2001,Data!$F$2:$F$2001,A10),0) -> 4.1968085 | H10: =INDEX(Assumptions!$B$8:$B$16,MATCH(A10,Assumptions!$A$8:$A$16,0)) -> 0.66 | I10: =RANK(D10,$D$5:$D$13) -> 3
A11: housewares | B11: =COUNTIFS(Data!$F$2:$F$2001,A11) -> 219 | C11: =SUMIFS(Data!$P$2:$P$2001,Data!$F$2:$F$2001,A11) -> 23840.83 | D11: =SUMIFS(Data!$S$2:$S$2001,Data!$F$2:$F$2001,A11) -> 4143.1075 | E11: =IFERROR(D11/C11,0) -> 0.17378202 | F11: =IFERROR(AVERAGEIFS(Data!$G$2:$G$2001,Data!$F$2:$F$2001,A11),0) -> 86.840868 | G11: =IFERROR(AVERAGEIFS(Data!$J$2:$J$2001,Data!$F$2:$F$2001,A11),0) -> 4.196347 | H11: =INDEX(Assumptions!$B$8:$B$16,MATCH(A11,Assumptions!$A$8:$A$16,0)) -> 0.63 | I11: =RANK(D11,$D$5:$D$13) -> 7
A12: toys | B12: =COUNTIFS(Data!$F$2:$F$2001,A12) -> 155 | C12: =SUMIFS(Data!$P$2:$P$2001,Data!$F$2:$F$2001,A12) -> 18719.23 | D12: =SUMIFS(Data!$S$2:$S$2001,Data!$F$2:$F$2001,A12) -> 4133.422 | E12: =IFERROR(D12/C12,0) -> 0.22081154 | F12: =IFERROR(AVERAGEIFS(Data!$G$2:$G$2001,Data!$F$2:$F$2001,A12),0) -> 99.128774 | G12: =IFERROR(AVERAGEIFS(Data!$J$2:$J$2001,Data!$F$2:$F$2001,A12),0) -> 4.2193548 | H12: =INDEX(Assumptions!$B$8:$B$16,MATCH(A12,Assumptions!$A$8:$A$16,0)) -> 0.6 | I12: =RANK(D12,$D$5:$D$13) -> 8
A13: auto | B13: =COUNTIFS(Data!$F$2:$F$2001,A13) -> 120 | C13: =SUMIFS(Data!$P$2:$P$2001,Data!$F$2:$F$2001,A13) -> 16372.64 | D13: =SUMIFS(Data!$S$2:$S$2001,Data!$F$2:$F$2001,A13) -> 2802.1188 | E13: =IFERROR(D13/C13,0) -> 0.17114642 | F13: =IFERROR(AVERAGEIFS(Data!$G$2:$G$2001,Data!$F$2:$F$2001,A13),0) -> 114.36325 | G13: =IFERROR(AVERAGEIFS(Data!$J$2:$J$2001,Data!$F$2:$F$2001,A13),0) -> 4.2666667 | H13: =INDEX(Assumptions!$B$8:$B$16,MATCH(A13,Assumptions!$A$8:$A$16,0)) -> 0.68 | I13: =RANK(D13,$D$5:$D$13) -> 9
